visagene/__init__.py
visagene/alighnment.py
visagene/analysis.py
visagene/base.py
visagene/detection.py
visagene/emap.bin
visagene/emap.py
visagene/embedding.py
visagene/enhance.py
visagene/paste.py
visagene/py.typed
visagene/schema.py
visagene/segmentation.py
visagene/swap.py
visagene/utils.py
visagene-0.4.3.dist-info/METADATA
visagene-0.4.3.dist-info/WHEEL
visagene-0.4.3.dist-info/licenses/LICENSE
visagene-0.4.3.dist-info/RECORD
