Metadata-Version: 2.4
Name: visagene
Version: 0.4.3
Summary: High-performance face detection, recognition, and manipulation library with GPU acceleration
Author-email: minamik <mia@sync.dev>
License: MIT
License-File: LICENSE
Keywords: cuda,face-detection,face-recognition,face-swap,gpu,onnx,tensorrt
Classifier: Development Status :: 4 - Beta
Classifier: Intended Audience :: Developers
Classifier: Intended Audience :: Science/Research
Classifier: License :: OSI Approved :: MIT License
Classifier: Programming Language :: Python :: 3
Classifier: Programming Language :: Python :: 3.12
Classifier: Programming Language :: Python :: 3.13
Classifier: Topic :: Scientific/Engineering :: Artificial Intelligence
Classifier: Topic :: Scientific/Engineering :: Image Recognition
Requires-Python: >=3.12
Requires-Dist: cupy-cuda12x>=13.4.1
Requires-Dist: numpy
Requires-Dist: onnx>=1.17.0
Requires-Dist: onnxruntime-gpu>=1.22.0
Requires-Dist: pixtreme[filter,upscale]>=0.8.5
Requires-Dist: pydantic
Requires-Dist: tensorrt-cu12>=10.11.0.33
Requires-Dist: torch
